[
  {
    "x": 10.193,
    "mu": 0.404,
    "sigma": 0.0858,
    "lower": 0.2325,
    "upper": 0.5755
  },
  {
    "x": 11.0678,
    "mu": 0.4061,
    "sigma": 0.0858,
    "lower": 0.2345,
    "upper": 0.5778
  },
  {
    "x": 11.9426,
    "mu": 0.4084,
    "sigma": 0.0859,
    "lower": 0.2366,
    "upper": 0.5801
  },
  {
    "x": 12.8175,
    "mu": 0.4107,
    "sigma": 0.0859,
    "lower": 0.2388,
    "upper": 0.5825
  },
  {
    "x": 13.6923,
    "mu": 0.4131,
    "sigma": 0.086,
    "lower": 0.2412,
    "upper": 0.5851
  },
  {
    "x": 14.5671,
    "mu": 0.4157,
    "sigma": 0.086,
    "lower": 0.2436,
    "upper": 0.5878
  },
  {
    "x": 15.4419,
    "mu": 0.4185,
    "sigma": 0.0861,
    "lower": 0.2463,
    "upper": 0.5906
  },
  {
    "x": 16.3167,
    "mu": 0.4213,
    "sigma": 0.0861,
    "lower": 0.249,
    "upper": 0.5936
  },
  {
    "x": 17.1915,
    "mu": 0.4243,
    "sigma": 0.0862,
    "lower": 0.2519,
    "upper": 0.5967
  },
  {
    "x": 18.0663,
    "mu": 0.4274,
    "sigma": 0.0863,
    "lower": 0.2549,
    "upper": 0.5999
  },
  {
    "x": 18.9411,
    "mu": 0.4306,
    "sigma": 0.0863,
    "lower": 0.258,
    "upper": 0.6032
  },
  {
    "x": 19.816,
    "mu": 0.4338,
    "sigma": 0.0864,
    "lower": 0.2611,
    "upper": 0.6066
  },
  {
    "x": 20.6908,
    "mu": 0.437,
    "sigma": 0.0864,
    "lower": 0.2641,
    "upper": 0.6098
  },
  {
    "x": 21.5656,
    "mu": 0.44,
    "sigma": 0.0865,
    "lower": 0.2671,
    "upper": 0.613
  },
  {
    "x": 22.4404,
    "mu": 0.4429,
    "sigma": 0.0865,
    "lower": 0.2698,
    "upper": 0.616
  },
  {
    "x": 23.3152,
    "mu": 0.4455,
    "sigma": 0.0866,
    "lower": 0.2723,
    "upper": 0.6187
  },
  {
    "x": 24.19,
    "mu": 0.4477,
    "sigma": 0.0867,
    "lower": 0.2744,
    "upper": 0.621
  },
  {
    "x": 25.0648,
    "mu": 0.4496,
    "sigma": 0.0867,
    "lower": 0.2762,
    "upper": 0.623
  },
  {
    "x": 25.9396,
    "mu": 0.4511,
    "sigma": 0.0868,
    "lower": 0.2776,
    "upper": 0.6247
  },
  {
    "x": 26.8145,
    "mu": 0.4522,
    "sigma": 0.0868,
    "lower": 0.2786,
    "upper": 0.6258
  },
  {
    "x": 27.6893,
    "mu": 0.4528,
    "sigma": 0.0869,
    "lower": 0.2791,
    "upper": 0.6266
  },
  {
    "x": 28.5641,
    "mu": 0.453,
    "sigma": 0.0869,
    "lower": 0.2791,
    "upper": 0.6269
  },
  {
    "x": 29.4389,
    "mu": 0.4528,
    "sigma": 0.087,
    "lower": 0.2789,
    "upper": 0.6268
  },
  {
    "x": 30.3137,
    "mu": 0.4524,
    "sigma": 0.087,
    "lower": 0.2783,
    "upper": 0.6265
  },
  {
    "x": 31.1885,
    "mu": 0.4516,
    "sigma": 0.0871,
    "lower": 0.2774,
    "upper": 0.6258
  },
  {
    "x": 32.0633,
    "mu": 0.4508,
    "sigma": 0.0872,
    "lower": 0.2764,
    "upper": 0.6251
  },
  {
    "x": 32.9381,
    "mu": 0.4497,
    "sigma": 0.0872,
    "lower": 0.2753,
    "upper": 0.6242
  },
  {
    "x": 33.813,
    "mu": 0.4486,
    "sigma": 0.0873,
    "lower": 0.2741,
    "upper": 0.6232
  },
  {
    "x": 34.6878,
    "mu": 0.4475,
    "sigma": 0.0873,
    "lower": 0.2728,
    "upper": 0.6221
  },
  {
    "x": 35.5626,
    "mu": 0.4463,
    "sigma": 0.0874,
    "lower": 0.2715,
    "upper": 0.6211
  },
  {
    "x": 36.4374,
    "mu": 0.4452,
    "sigma": 0.0874,
    "lower": 0.2703,
    "upper": 0.6201
  },
  {
    "x": 37.3122,
    "mu": 0.4441,
    "sigma": 0.0875,
    "lower": 0.2691,
    "upper": 0.6191
  },
  {
    "x": 38.187,
    "mu": 0.4431,
    "sigma": 0.0876,
    "lower": 0.268,
    "upper": 0.6182
  },
  {
    "x": 39.0618,
    "mu": 0.4422,
    "sigma": 0.0876,
    "lower": 0.267,
    "upper": 0.6174
  },
  {
    "x": 39.9366,
    "mu": 0.4413,
    "sigma": 0.0877,
    "lower": 0.2659,
    "upper": 0.6166
  },
  {
    "x": 40.8115,
    "mu": 0.4404,
    "sigma": 0.0877,
    "lower": 0.265,
    "upper": 0.6159
  },
  {
    "x": 41.6863,
    "mu": 0.4396,
    "sigma": 0.0878,
    "lower": 0.2641,
    "upper": 0.6152
  },
  {
    "x": 42.5611,
    "mu": 0.4389,
    "sigma": 0.0878,
    "lower": 0.2632,
    "upper": 0.6146
  },
  {
    "x": 43.4359,
    "mu": 0.4381,
    "sigma": 0.0879,
    "lower": 0.2624,
    "upper": 0.6139
  },
  {
    "x": 44.3107,
    "mu": 0.4374,
    "sigma": 0.088,
    "lower": 0.2615,
    "upper": 0.6133
  },
  {
    "x": 45.1855,
    "mu": 0.4367,
    "sigma": 0.088,
    "lower": 0.2607,
    "upper": 0.6127
  },
  {
    "x": 46.0603,
    "mu": 0.436,
    "sigma": 0.0881,
    "lower": 0.2598,
    "upper": 0.6121
  },
  {
    "x": 46.9351,
    "mu": 0.4352,
    "sigma": 0.0881,
    "lower": 0.259,
    "upper": 0.6115
  },
  {
    "x": 47.81,
    "mu": 0.4345,
    "sigma": 0.0882,
    "lower": 0.2581,
    "upper": 0.6108
  },
  {
    "x": 48.6848,
    "mu": 0.4336,
    "sigma": 0.0882,
    "lower": 0.2571,
    "upper": 0.6101
  },
  {
    "x": 49.5596,
    "mu": 0.4328,
    "sigma": 0.0883,
    "lower": 0.2562,
    "upper": 0.6094
  },
  {
    "x": 50.4344,
    "mu": 0.4318,
    "sigma": 0.0884,
    "lower": 0.2551,
    "upper": 0.6086
  },
  {
    "x": 51.3092,
    "mu": 0.4309,
    "sigma": 0.0884,
    "lower": 0.2541,
    "upper": 0.6077
  },
  {
    "x": 52.184,
    "mu": 0.4299,
    "sigma": 0.0885,
    "lower": 0.2529,
    "upper": 0.6068
  },
  {
    "x": 53.0588,
    "mu": 0.4288,
    "sigma": 0.0885,
    "lower": 0.2518,
    "upper": 0.6059
  },
  {
    "x": 53.9336,
    "mu": 0.4277,
    "sigma": 0.0886,
    "lower": 0.2506,
    "upper": 0.6049
  },
  {
    "x": 54.8085,
    "mu": 0.4266,
    "sigma": 0.0886,
    "lower": 0.2493,
    "upper": 0.6039
  },
  {
    "x": 55.6833,
    "mu": 0.4255,
    "sigma": 0.0887,
    "lower": 0.2481,
    "upper": 0.6029
  },
  {
    "x": 56.5581,
    "mu": 0.4244,
    "sigma": 0.0888,
    "lower": 0.2469,
    "upper": 0.6019
  },
  {
    "x": 57.4329,
    "mu": 0.4234,
    "sigma": 0.0888,
    "lower": 0.2457,
    "upper": 0.601
  },
  {
    "x": 58.3077,
    "mu": 0.4224,
    "sigma": 0.0889,
    "lower": 0.2446,
    "upper": 0.6001
  },
  {
    "x": 59.1825,
    "mu": 0.4215,
    "sigma": 0.0889,
    "lower": 0.2436,
    "upper": 0.5994
  },
  {
    "x": 60.0573,
    "mu": 0.4207,
    "sigma": 0.089,
    "lower": 0.2427,
    "upper": 0.5987
  },
  {
    "x": 60.9321,
    "mu": 0.42,
    "sigma": 0.089,
    "lower": 0.2419,
    "upper": 0.5981
  },
  {
    "x": 61.807,
    "mu": 0.4193,
    "sigma": 0.0891,
    "lower": 0.2411,
    "upper": 0.5975
  },
  {
    "x": 62.6818,
    "mu": 0.4188,
    "sigma": 0.0892,
    "lower": 0.2404,
    "upper": 0.5971
  },
  {
    "x": 63.5566,
    "mu": 0.4182,
    "sigma": 0.0892,
    "lower": 0.2398,
    "upper": 0.5967
  },
  {
    "x": 64.4314,
    "mu": 0.4177,
    "sigma": 0.0893,
    "lower": 0.2391,
    "upper": 0.5963
  },
  {
    "x": 65.3062,
    "mu": 0.4171,
    "sigma": 0.0893,
    "lower": 0.2385,
    "upper": 0.5958
  },
  {
    "x": 66.181,
    "mu": 0.4165,
    "sigma": 0.0894,
    "lower": 0.2377,
    "upper": 0.5953
  },
  {
    "x": 67.0558,
    "mu": 0.4157,
    "sigma": 0.0895,
    "lower": 0.2368,
    "upper": 0.5946
  },
  {
    "x": 67.9306,
    "mu": 0.4147,
    "sigma": 0.0895,
    "lower": 0.2357,
    "upper": 0.5937
  },
  {
    "x": 68.8055,
    "mu": 0.4136,
    "sigma": 0.0896,
    "lower": 0.2345,
    "upper": 0.5927
  },
  {
    "x": 69.6803,
    "mu": 0.4124,
    "sigma": 0.0896,
    "lower": 0.2331,
    "upper": 0.5916
  },
  {
    "x": 70.5551,
    "mu": 0.411,
    "sigma": 0.0897,
    "lower": 0.2316,
    "upper": 0.5904
  },
  {
    "x": 71.4299,
    "mu": 0.4095,
    "sigma": 0.0897,
    "lower": 0.23,
    "upper": 0.589
  },
  {
    "x": 72.3047,
    "mu": 0.4079,
    "sigma": 0.0898,
    "lower": 0.2283,
    "upper": 0.5875
  },
  {
    "x": 73.1795,
    "mu": 0.4063,
    "sigma": 0.0899,
    "lower": 0.2266,
    "upper": 0.586
  },
  {
    "x": 74.0543,
    "mu": 0.4046,
    "sigma": 0.0899,
    "lower": 0.2248,
    "upper": 0.5845
  },
  {
    "x": 74.9291,
    "mu": 0.4031,
    "sigma": 0.09,
    "lower": 0.2231,
    "upper": 0.583
  },
  {
    "x": 75.804,
    "mu": 0.4016,
    "sigma": 0.09,
    "lower": 0.2215,
    "upper": 0.5817
  },
  {
    "x": 76.6788,
    "mu": 0.4003,
    "sigma": 0.0901,
    "lower": 0.2201,
    "upper": 0.5805
  },
  {
    "x": 77.5536,
    "mu": 0.3991,
    "sigma": 0.0901,
    "lower": 0.2188,
    "upper": 0.5794
  },
  {
    "x": 78.4284,
    "mu": 0.3981,
    "sigma": 0.0902,
    "lower": 0.2177,
    "upper": 0.5786
  },
  {
    "x": 79.3032,
    "mu": 0.3974,
    "sigma": 0.0903,
    "lower": 0.2168,
    "upper": 0.5779
  },
  {
    "x": 80.178,
    "mu": 0.3968,
    "sigma": 0.0903,
    "lower": 0.2161,
    "upper": 0.5774
  },
  {
    "x": 81.0528,
    "mu": 0.3964,
    "sigma": 0.0904,
    "lower": 0.2157,
    "upper": 0.5772
  },
  {
    "x": 81.9276,
    "mu": 0.3963,
    "sigma": 0.0904,
    "lower": 0.2154,
    "upper": 0.5771
  },
  {
    "x": 82.8025,
    "mu": 0.3962,
    "sigma": 0.0905,
    "lower": 0.2152,
    "upper": 0.5772
  },
  {
    "x": 83.6773,
    "mu": 0.3964,
    "sigma": 0.0906,
    "lower": 0.2153,
    "upper": 0.5775
  },
  {
    "x": 84.5521,
    "mu": 0.3966,
    "sigma": 0.0906,
    "lower": 0.2154,
    "upper": 0.5778
  },
  {
    "x": 85.4269,
    "mu": 0.3969,
    "sigma": 0.0907,
    "lower": 0.2156,
    "upper": 0.5783
  },
  {
    "x": 86.3017,
    "mu": 0.3973,
    "sigma": 0.0907,
    "lower": 0.2159,
    "upper": 0.5788
  },
  {
    "x": 87.1765,
    "mu": 0.3978,
    "sigma": 0.0908,
    "lower": 0.2162,
    "upper": 0.5794
  },
  {
    "x": 88.0513,
    "mu": 0.3983,
    "sigma": 0.0909,
    "lower": 0.2165,
    "upper": 0.58
  },
  {
    "x": 88.9261,
    "mu": 0.3987,
    "sigma": 0.0909,
    "lower": 0.2169,
    "upper": 0.5806
  },
  {
    "x": 89.801,
    "mu": 0.3992,
    "sigma": 0.091,
    "lower": 0.2173,
    "upper": 0.5811
  },
  {
    "x": 90.6758,
    "mu": 0.3997,
    "sigma": 0.091,
    "lower": 0.2176,
    "upper": 0.5817
  },
  {
    "x": 91.5506,
    "mu": 0.4001,
    "sigma": 0.0911,
    "lower": 0.2179,
    "upper": 0.5823
  },
  {
    "x": 92.4254,
    "mu": 0.4006,
    "sigma": 0.0911,
    "lower": 0.2183,
    "upper": 0.5829
  },
  {
    "x": 93.3002,
    "mu": 0.401,
    "sigma": 0.0912,
    "lower": 0.2186,
    "upper": 0.5834
  },
  {
    "x": 94.175,
    "mu": 0.4014,
    "sigma": 0.0913,
    "lower": 0.2189,
    "upper": 0.584
  },
  {
    "x": 95.0498,
    "mu": 0.4019,
    "sigma": 0.0913,
    "lower": 0.2192,
    "upper": 0.5845
  },
  {
    "x": 95.9246,
    "mu": 0.4023,
    "sigma": 0.0914,
    "lower": 0.2195,
    "upper": 0.5851
  },
  {
    "x": 96.7995,
    "mu": 0.4027,
    "sigma": 0.0914,
    "lower": 0.2198,
    "upper": 0.5856
  }
]
