[
  {
    "x": 10.193,
    "mu": 0.2408,
    "sigma": 0.1936,
    "lower": -0.1464,
    "upper": 0.628
  },
  {
    "x": 10.8189,
    "mu": 0.2408,
    "sigma": 0.1838,
    "lower": -0.1268,
    "upper": 0.6083
  },
  {
    "x": 11.4448,
    "mu": 0.2408,
    "sigma": 0.1745,
    "lower": -0.1082,
    "upper": 0.5898
  },
  {
    "x": 12.0707,
    "mu": 0.2408,
    "sigma": 0.1657,
    "lower": -0.0907,
    "upper": 0.5722
  },
  {
    "x": 12.6966,
    "mu": 0.2408,
    "sigma": 0.1574,
    "lower": -0.0741,
    "upper": 0.5556
  },
  {
    "x": 13.3225,
    "mu": 0.2408,
    "sigma": 0.1496,
    "lower": -0.0585,
    "upper": 0.54
  },
  {
    "x": 13.9484,
    "mu": 0.2408,
    "sigma": 0.1423,
    "lower": -0.0438,
    "upper": 0.5253
  },
  {
    "x": 14.5742,
    "mu": 0.2408,
    "sigma": 0.1354,
    "lower": -0.03,
    "upper": 0.5116
  },
  {
    "x": 15.2001,
    "mu": 0.2408,
    "sigma": 0.129,
    "lower": -0.0171,
    "upper": 0.4987
  },
  {
    "x": 15.826,
    "mu": 0.2408,
    "sigma": 0.1229,
    "lower": -0.0051,
    "upper": 0.4867
  },
  {
    "x": 16.4519,
    "mu": 0.2408,
    "sigma": 0.1174,
    "lower": 0.006,
    "upper": 0.4755
  },
  {
    "x": 17.0778,
    "mu": 0.2408,
    "sigma": 0.1122,
    "lower": 0.0164,
    "upper": 0.4652
  },
  {
    "x": 17.7037,
    "mu": 0.2408,
    "sigma": 0.1074,
    "lower": 0.026,
    "upper": 0.4556
  },
  {
    "x": 18.3296,
    "mu": 0.2408,
    "sigma": 0.103,
    "lower": 0.0348,
    "upper": 0.4468
  },
  {
    "x": 18.9555,
    "mu": 0.2408,
    "sigma": 0.0989,
    "lower": 0.0429,
    "upper": 0.4387
  },
  {
    "x": 19.5814,
    "mu": 0.2408,
    "sigma": 0.0952,
    "lower": 0.0503,
    "upper": 0.4312
  },
  {
    "x": 20.2072,
    "mu": 0.2408,
    "sigma": 0.0918,
    "lower": 0.0571,
    "upper": 0.4244
  },
  {
    "x": 20.8331,
    "mu": 0.2408,
    "sigma": 0.0887,
    "lower": 0.0633,
    "upper": 0.4182
  },
  {
    "x": 21.459,
    "mu": 0.2408,
    "sigma": 0.0859,
    "lower": 0.069,
    "upper": 0.4125
  },
  {
    "x": 22.0849,
    "mu": 0.2408,
    "sigma": 0.0833,
    "lower": 0.0742,
    "upper": 0.4074
  },
  {
    "x": 22.7108,
    "mu": 0.2408,
    "sigma": 0.0809,
    "lower": 0.0789,
    "upper": 0.4027
  },
  {
    "x": 23.3367,
    "mu": 0.2408,
    "sigma": 0.0788,
    "lower": 0.0832,
    "upper": 0.3984
  },
  {
    "x": 23.9626,
    "mu": 0.2408,
    "sigma": 0.0768,
    "lower": 0.0871,
    "upper": 0.3944
  },
  {
    "x": 24.5885,
    "mu": 0.2408,
    "sigma": 0.075,
    "lower": 0.0908,
    "upper": 0.3908
  },
  {
    "x": 25.2144,
    "mu": 0.2408,
    "sigma": 0.0733,
    "lower": 0.0941,
    "upper": 0.3874
  },
  {
    "x": 25.8403,
    "mu": 0.2408,
    "sigma": 0.0718,
    "lower": 0.0973,
    "upper": 0.3843
  },
  {
    "x": 26.4661,
    "mu": 0.2408,
    "sigma": 0.0703,
    "lower": 0.1002,
    "upper": 0.3814
  },
  {
    "x": 27.092,
    "mu": 0.2408,
    "sigma": 0.069,
    "lower": 0.1029,
    "upper": 0.3787
  },
  {
    "x": 27.7179,
    "mu": 0.2408,
    "sigma": 0.0677,
    "lower": 0.1054,
    "upper": 0.3761
  },
  {
    "x": 28.3438,
    "mu": 0.2408,
    "sigma": 0.0665,
    "lower": 0.1078,
    "upper": 0.3738
  },
  {
    "x": 28.9697,
    "mu": 0.2408,
    "sigma": 0.0653,
    "lower": 0.1101,
    "upper": 0.3715
  },
  {
    "x": 29.5956,
    "mu": 0.2408,
    "sigma": 0.0643,
    "lower": 0.1122,
    "upper": 0.3694
  },
  {
    "x": 30.2215,
    "mu": 0.2408,
    "sigma": 0.0633,
    "lower": 0.1142,
    "upper": 0.3674
  },
  {
    "x": 30.8474,
    "mu": 0.2408,
    "sigma": 0.0623,
    "lower": 0.1161,
    "upper": 0.3655
  },
  {
    "x": 31.4733,
    "mu": 0.2408,
    "sigma": 0.0615,
    "lower": 0.1179,
    "upper": 0.3637
  },
  {
    "x": 32.0991,
    "mu": 0.2408,
    "sigma": 0.0606,
    "lower": 0.1196,
    "upper": 0.3621
  },
  {
    "x": 32.725,
    "mu": 0.2408,
    "sigma": 0.0599,
    "lower": 0.1211,
    "upper": 0.3605
  },
  {
    "x": 33.3509,
    "mu": 0.2408,
    "sigma": 0.0591,
    "lower": 0.1226,
    "upper": 0.3591
  },
  {
    "x": 33.9768,
    "mu": 0.2408,
    "sigma": 0.0585,
    "lower": 0.1239,
    "upper": 0.3578
  },
  {
    "x": 34.6027,
    "mu": 0.2408,
    "sigma": 0.0579,
    "lower": 0.1251,
    "upper": 0.3565
  },
  {
    "x": 35.2286,
    "mu": 0.2408,
    "sigma": 0.0573,
    "lower": 0.1262,
    "upper": 0.3554
  },
  {
    "x": 35.8545,
    "mu": 0.2408,
    "sigma": 0.0568,
    "lower": 0.1273,
    "upper": 0.3544
  },
  {
    "x": 36.4804,
    "mu": 0.2408,
    "sigma": 0.0563,
    "lower": 0.1282,
    "upper": 0.3535
  },
  {
    "x": 37.1063,
    "mu": 0.2408,
    "sigma": 0.0559,
    "lower": 0.129,
    "upper": 0.3527
  },
  {
    "x": 37.7321,
    "mu": 0.2408,
    "sigma": 0.0556,
    "lower": 0.1297,
    "upper": 0.352
  },
  {
    "x": 38.358,
    "mu": 0.2408,
    "sigma": 0.0552,
    "lower": 0.1304,
    "upper": 0.3513
  },
  {
    "x": 38.9839,
    "mu": 0.2409,
    "sigma": 0.055,
    "lower": 0.131,
    "upper": 0.3508
  },
  {
    "x": 39.6098,
    "mu": 0.2409,
    "sigma": 0.0547,
    "lower": 0.1314,
    "upper": 0.3503
  },
  {
    "x": 40.2357,
    "mu": 0.2409,
    "sigma": 0.0545,
    "lower": 0.1318,
    "upper": 0.3499
  },
  {
    "x": 40.8616,
    "mu": 0.2409,
    "sigma": 0.0543,
    "lower": 0.1322,
    "upper": 0.3496
  },
  {
    "x": 41.4875,
    "mu": 0.2409,
    "sigma": 0.0542,
    "lower": 0.1324,
    "upper": 0.3493
  },
  {
    "x": 42.1134,
    "mu": 0.2409,
    "sigma": 0.0541,
    "lower": 0.1326,
    "upper": 0.3491
  },
  {
    "x": 42.7393,
    "mu": 0.2409,
    "sigma": 0.0541,
    "lower": 0.1327,
    "upper": 0.349
  },
  {
    "x": 43.3652,
    "mu": 0.2409,
    "sigma": 0.0541,
    "lower": 0.1328,
    "upper": 0.349
  },
  {
    "x": 43.991,
    "mu": 0.2409,
    "sigma": 0.0541,
    "lower": 0.1327,
    "upper": 0.349
  },
  {
    "x": 44.6169,
    "mu": 0.2409,
    "sigma": 0.0541,
    "lower": 0.1327,
    "upper": 0.3491
  },
  {
    "x": 45.2428,
    "mu": 0.2409,
    "sigma": 0.0542,
    "lower": 0.1325,
    "upper": 0.3493
  },
  {
    "x": 45.8687,
    "mu": 0.2409,
    "sigma": 0.0543,
    "lower": 0.1323,
    "upper": 0.3495
  },
  {
    "x": 46.4946,
    "mu": 0.2409,
    "sigma": 0.0544,
    "lower": 0.132,
    "upper": 0.3498
  },
  {
    "x": 47.1205,
    "mu": 0.2409,
    "sigma": 0.0546,
    "lower": 0.1317,
    "upper": 0.3501
  },
  {
    "x": 47.7464,
    "mu": 0.2409,
    "sigma": 0.0548,
    "lower": 0.1313,
    "upper": 0.3505
  },
  {
    "x": 48.3723,
    "mu": 0.2409,
    "sigma": 0.055,
    "lower": 0.1309,
    "upper": 0.3509
  },
  {
    "x": 48.9982,
    "mu": 0.2409,
    "sigma": 0.0553,
    "lower": 0.1304,
    "upper": 0.3515
  },
  {
    "x": 49.624,
    "mu": 0.2409,
    "sigma": 0.0555,
    "lower": 0.1298,
    "upper": 0.352
  },
  {
    "x": 50.2499,
    "mu": 0.2409,
    "sigma": 0.0559,
    "lower": 0.1292,
    "upper": 0.3526
  },
  {
    "x": 50.8758,
    "mu": 0.2409,
    "sigma": 0.0562,
    "lower": 0.1286,
    "upper": 0.3533
  },
  {
    "x": 51.5017,
    "mu": 0.2409,
    "sigma": 0.0565,
    "lower": 0.1279,
    "upper": 0.354
  },
  {
    "x": 52.1276,
    "mu": 0.2409,
    "sigma": 0.0569,
    "lower": 0.1271,
    "upper": 0.3548
  },
  {
    "x": 52.7535,
    "mu": 0.241,
    "sigma": 0.0573,
    "lower": 0.1263,
    "upper": 0.3556
  },
  {
    "x": 53.3794,
    "mu": 0.241,
    "sigma": 0.0578,
    "lower": 0.1254,
    "upper": 0.3565
  },
  {
    "x": 54.0053,
    "mu": 0.241,
    "sigma": 0.0582,
    "lower": 0.1245,
    "upper": 0.3574
  },
  {
    "x": 54.6312,
    "mu": 0.241,
    "sigma": 0.0587,
    "lower": 0.1235,
    "upper": 0.3584
  },
  {
    "x": 55.257,
    "mu": 0.241,
    "sigma": 0.0592,
    "lower": 0.1225,
    "upper": 0.3594
  },
  {
    "x": 55.8829,
    "mu": 0.241,
    "sigma": 0.0597,
    "lower": 0.1215,
    "upper": 0.3604
  },
  {
    "x": 56.5088,
    "mu": 0.241,
    "sigma": 0.0603,
    "lower": 0.1204,
    "upper": 0.3615
  },
  {
    "x": 57.1347,
    "mu": 0.241,
    "sigma": 0.0608,
    "lower": 0.1193,
    "upper": 0.3626
  },
  {
    "x": 57.7606,
    "mu": 0.241,
    "sigma": 0.0614,
    "lower": 0.1182,
    "upper": 0.3638
  },
  {
    "x": 58.3865,
    "mu": 0.241,
    "sigma": 0.062,
    "lower": 0.1171,
    "upper": 0.3649
  },
  {
    "x": 59.0124,
    "mu": 0.241,
    "sigma": 0.0626,
    "lower": 0.1159,
    "upper": 0.3661
  },
  {
    "x": 59.6383,
    "mu": 0.241,
    "sigma": 0.0631,
    "lower": 0.1147,
    "upper": 0.3673
  },
  {
    "x": 60.2642,
    "mu": 0.241,
    "sigma": 0.0637,
    "lower": 0.1136,
    "upper": 0.3685
  },
  {
    "x": 60.8901,
    "mu": 0.241,
    "sigma": 0.0643,
    "lower": 0.1124,
    "upper": 0.3696
  },
  {
    "x": 61.5159,
    "mu": 0.241,
    "sigma": 0.0649,
    "lower": 0.1112,
    "upper": 0.3708
  },
  {
    "x": 62.1418,
    "mu": 0.241,
    "sigma": 0.0655,
    "lower": 0.1101,
    "upper": 0.3719
  },
  {
    "x": 62.7677,
    "mu": 0.241,
    "sigma": 0.066,
    "lower": 0.109,
    "upper": 0.373
  },
  {
    "x": 63.3936,
    "mu": 0.241,
    "sigma": 0.0666,
    "lower": 0.1079,
    "upper": 0.3742
  },
  {
    "x": 64.0195,
    "mu": 0.241,
    "sigma": 0.0671,
    "lower": 0.1068,
    "upper": 0.3752
  },
  {
    "x": 64.6454,
    "mu": 0.241,
    "sigma": 0.0676,
    "lower": 0.1058,
    "upper": 0.3763
  },
  {
    "x": 65.2713,
    "mu": 0.241,
    "sigma": 0.0681,
    "lower": 0.1047,
    "upper": 0.3773
  },
  {
    "x": 65.8972,
    "mu": 0.241,
    "sigma": 0.0687,
    "lower": 0.1037,
    "upper": 0.3784
  },
  {
    "x": 66.5231,
    "mu": 0.241,
    "sigma": 0.0692,
    "lower": 0.1027,
    "upper": 0.3794
  },
  {
    "x": 67.1489,
    "mu": 0.241,
    "sigma": 0.0697,
    "lower": 0.1017,
    "upper": 0.3804
  },
  {
    "x": 67.7748,
    "mu": 0.241,
    "sigma": 0.0701,
    "lower": 0.1007,
    "upper": 0.3813
  },
  {
    "x": 68.4007,
    "mu": 0.241,
    "sigma": 0.0706,
    "lower": 0.0998,
    "upper": 0.3823
  },
  {
    "x": 69.0266,
    "mu": 0.241,
    "sigma": 0.0711,
    "lower": 0.0988,
    "upper": 0.3833
  },
  {
    "x": 69.6525,
    "mu": 0.241,
    "sigma": 0.0716,
    "lower": 0.0978,
    "upper": 0.3842
  },
  {
    "x": 70.2784,
    "mu": 0.241,
    "sigma": 0.0721,
    "lower": 0.0969,
    "upper": 0.3852
  },
  {
    "x": 70.9043,
    "mu": 0.2411,
    "sigma": 0.0726,
    "lower": 0.0959,
    "upper": 0.3862
  },
  {
    "x": 71.5302,
    "mu": 0.2411,
    "sigma": 0.073,
    "lower": 0.095,
    "upper": 0.3871
  },
  {
    "x": 72.1561,
    "mu": 0.2411,
    "sigma": 0.0735,
    "lower": 0.094,
    "upper": 0.3881
  }
]
