[
  {
    "x": 10.193,
    "mu": 0.2697,
    "sigma": 0.2554,
    "lower": -0.241,
    "upper": 0.7804
  },
  {
    "x": 10.8189,
    "mu": 0.2692,
    "sigma": 0.2432,
    "lower": -0.2171,
    "upper": 0.7556
  },
  {
    "x": 11.4448,
    "mu": 0.2687,
    "sigma": 0.2316,
    "lower": -0.1944,
    "upper": 0.7319
  },
  {
    "x": 12.0707,
    "mu": 0.2682,
    "sigma": 0.2205,
    "lower": -0.1729,
    "upper": 0.7092
  },
  {
    "x": 12.6966,
    "mu": 0.2676,
    "sigma": 0.21,
    "lower": -0.1524,
    "upper": 0.6876
  },
  {
    "x": 13.3225,
    "mu": 0.267,
    "sigma": 0.1999,
    "lower": -0.1329,
    "upper": 0.6668
  },
  {
    "x": 13.9484,
    "mu": 0.2663,
    "sigma": 0.1904,
    "lower": -0.1144,
    "upper": 0.647
  },
  {
    "x": 14.5742,
    "mu": 0.2655,
    "sigma": 0.1812,
    "lower": -0.0969,
    "upper": 0.628
  },
  {
    "x": 15.2001,
    "mu": 0.2647,
    "sigma": 0.1726,
    "lower": -0.0804,
    "upper": 0.6098
  },
  {
    "x": 15.826,
    "mu": 0.2638,
    "sigma": 0.1643,
    "lower": -0.0649,
    "upper": 0.5924
  },
  {
    "x": 16.4519,
    "mu": 0.2627,
    "sigma": 0.1565,
    "lower": -0.0503,
    "upper": 0.5757
  },
  {
    "x": 17.0778,
    "mu": 0.2615,
    "sigma": 0.1491,
    "lower": -0.0366,
    "upper": 0.5597
  },
  {
    "x": 17.7037,
    "mu": 0.2603,
    "sigma": 0.1421,
    "lower": -0.0239,
    "upper": 0.5444
  },
  {
    "x": 18.3296,
    "mu": 0.2589,
    "sigma": 0.1355,
    "lower": -0.012,
    "upper": 0.5298
  },
  {
    "x": 18.9555,
    "mu": 0.2574,
    "sigma": 0.1292,
    "lower": -0.001,
    "upper": 0.5158
  },
  {
    "x": 19.5814,
    "mu": 0.2557,
    "sigma": 0.1233,
    "lower": 0.0091,
    "upper": 0.5024
  },
  {
    "x": 20.2072,
    "mu": 0.254,
    "sigma": 0.1178,
    "lower": 0.0184,
    "upper": 0.4896
  },
  {
    "x": 20.8331,
    "mu": 0.2523,
    "sigma": 0.1127,
    "lower": 0.027,
    "upper": 0.4776
  },
  {
    "x": 21.459,
    "mu": 0.2505,
    "sigma": 0.1079,
    "lower": 0.0348,
    "upper": 0.4662
  },
  {
    "x": 22.0849,
    "mu": 0.2488,
    "sigma": 0.1034,
    "lower": 0.0419,
    "upper": 0.4556
  },
  {
    "x": 22.7108,
    "mu": 0.2471,
    "sigma": 0.0994,
    "lower": 0.0484,
    "upper": 0.4458
  },
  {
    "x": 23.3367,
    "mu": 0.2455,
    "sigma": 0.0956,
    "lower": 0.0543,
    "upper": 0.4367
  },
  {
    "x": 23.9626,
    "mu": 0.244,
    "sigma": 0.0922,
    "lower": 0.0597,
    "upper": 0.4283
  },
  {
    "x": 24.5885,
    "mu": 0.2427,
    "sigma": 0.089,
    "lower": 0.0646,
    "upper": 0.4207
  },
  {
    "x": 25.2144,
    "mu": 0.2415,
    "sigma": 0.0861,
    "lower": 0.0692,
    "upper": 0.4138
  },
  {
    "x": 25.8403,
    "mu": 0.2405,
    "sigma": 0.0835,
    "lower": 0.0735,
    "upper": 0.4076
  },
  {
    "x": 26.4661,
    "mu": 0.2398,
    "sigma": 0.0811,
    "lower": 0.0775,
    "upper": 0.402
  },
  {
    "x": 27.092,
    "mu": 0.2391,
    "sigma": 0.079,
    "lower": 0.0812,
    "upper": 0.3971
  },
  {
    "x": 27.7179,
    "mu": 0.2387,
    "sigma": 0.077,
    "lower": 0.0847,
    "upper": 0.3926
  },
  {
    "x": 28.3438,
    "mu": 0.2383,
    "sigma": 0.0752,
    "lower": 0.088,
    "upper": 0.3887
  },
  {
    "x": 28.9697,
    "mu": 0.2381,
    "sigma": 0.0735,
    "lower": 0.0911,
    "upper": 0.3851
  },
  {
    "x": 29.5956,
    "mu": 0.2379,
    "sigma": 0.072,
    "lower": 0.0939,
    "upper": 0.382
  },
  {
    "x": 30.2215,
    "mu": 0.2378,
    "sigma": 0.0707,
    "lower": 0.0965,
    "upper": 0.3792
  },
  {
    "x": 30.8474,
    "mu": 0.2378,
    "sigma": 0.0694,
    "lower": 0.099,
    "upper": 0.3766
  },
  {
    "x": 31.4733,
    "mu": 0.2378,
    "sigma": 0.0683,
    "lower": 0.1012,
    "upper": 0.3743
  },
  {
    "x": 32.0991,
    "mu": 0.2377,
    "sigma": 0.0673,
    "lower": 0.1032,
    "upper": 0.3723
  },
  {
    "x": 32.725,
    "mu": 0.2377,
    "sigma": 0.0663,
    "lower": 0.105,
    "upper": 0.3704
  },
  {
    "x": 33.3509,
    "mu": 0.2378,
    "sigma": 0.0655,
    "lower": 0.1067,
    "upper": 0.3688
  },
  {
    "x": 33.9768,
    "mu": 0.2378,
    "sigma": 0.0648,
    "lower": 0.1082,
    "upper": 0.3674
  },
  {
    "x": 34.6027,
    "mu": 0.2379,
    "sigma": 0.0641,
    "lower": 0.1096,
    "upper": 0.3661
  },
  {
    "x": 35.2286,
    "mu": 0.238,
    "sigma": 0.0636,
    "lower": 0.1109,
    "upper": 0.3651
  },
  {
    "x": 35.8545,
    "mu": 0.2381,
    "sigma": 0.0631,
    "lower": 0.112,
    "upper": 0.3642
  },
  {
    "x": 36.4804,
    "mu": 0.2383,
    "sigma": 0.0626,
    "lower": 0.1131,
    "upper": 0.3636
  },
  {
    "x": 37.1063,
    "mu": 0.2386,
    "sigma": 0.0623,
    "lower": 0.1141,
    "upper": 0.3631
  },
  {
    "x": 37.7321,
    "mu": 0.2389,
    "sigma": 0.062,
    "lower": 0.115,
    "upper": 0.3628
  },
  {
    "x": 38.358,
    "mu": 0.2392,
    "sigma": 0.0617,
    "lower": 0.1158,
    "upper": 0.3627
  },
  {
    "x": 38.9839,
    "mu": 0.2396,
    "sigma": 0.0615,
    "lower": 0.1165,
    "upper": 0.3627
  },
  {
    "x": 39.6098,
    "mu": 0.2401,
    "sigma": 0.0614,
    "lower": 0.1172,
    "upper": 0.3629
  },
  {
    "x": 40.2357,
    "mu": 0.2406,
    "sigma": 0.0613,
    "lower": 0.1179,
    "upper": 0.3632
  },
  {
    "x": 40.8616,
    "mu": 0.2411,
    "sigma": 0.0613,
    "lower": 0.1184,
    "upper": 0.3637
  },
  {
    "x": 41.4875,
    "mu": 0.2416,
    "sigma": 0.0613,
    "lower": 0.119,
    "upper": 0.3643
  },
  {
    "x": 42.1134,
    "mu": 0.2422,
    "sigma": 0.0614,
    "lower": 0.1194,
    "upper": 0.365
  },
  {
    "x": 42.7393,
    "mu": 0.2428,
    "sigma": 0.0615,
    "lower": 0.1198,
    "upper": 0.3658
  },
  {
    "x": 43.3652,
    "mu": 0.2434,
    "sigma": 0.0616,
    "lower": 0.1202,
    "upper": 0.3667
  },
  {
    "x": 43.991,
    "mu": 0.2441,
    "sigma": 0.0618,
    "lower": 0.1205,
    "upper": 0.3677
  },
  {
    "x": 44.6169,
    "mu": 0.2448,
    "sigma": 0.062,
    "lower": 0.1208,
    "upper": 0.3688
  },
  {
    "x": 45.2428,
    "mu": 0.2455,
    "sigma": 0.0622,
    "lower": 0.1211,
    "upper": 0.3699
  },
  {
    "x": 45.8687,
    "mu": 0.2462,
    "sigma": 0.0625,
    "lower": 0.1213,
    "upper": 0.3712
  },
  {
    "x": 46.4946,
    "mu": 0.247,
    "sigma": 0.0628,
    "lower": 0.1215,
    "upper": 0.3725
  },
  {
    "x": 47.1205,
    "mu": 0.2477,
    "sigma": 0.0631,
    "lower": 0.1216,
    "upper": 0.3739
  },
  {
    "x": 47.7464,
    "mu": 0.2485,
    "sigma": 0.0634,
    "lower": 0.1217,
    "upper": 0.3753
  },
  {
    "x": 48.3723,
    "mu": 0.2493,
    "sigma": 0.0637,
    "lower": 0.1218,
    "upper": 0.3767
  },
  {
    "x": 48.9982,
    "mu": 0.2501,
    "sigma": 0.0641,
    "lower": 0.1219,
    "upper": 0.3782
  },
  {
    "x": 49.624,
    "mu": 0.2509,
    "sigma": 0.0644,
    "lower": 0.122,
    "upper": 0.3798
  },
  {
    "x": 50.2499,
    "mu": 0.2517,
    "sigma": 0.0648,
    "lower": 0.1221,
    "upper": 0.3813
  },
  {
    "x": 50.8758,
    "mu": 0.2525,
    "sigma": 0.0652,
    "lower": 0.1222,
    "upper": 0.3828
  },
  {
    "x": 51.5017,
    "mu": 0.2533,
    "sigma": 0.0655,
    "lower": 0.1223,
    "upper": 0.3844
  },
  {
    "x": 52.1276,
    "mu": 0.2541,
    "sigma": 0.0659,
    "lower": 0.1224,
    "upper": 0.3859
  },
  {
    "x": 52.7535,
    "mu": 0.2549,
    "sigma": 0.0662,
    "lower": 0.1225,
    "upper": 0.3873
  },
  {
    "x": 53.3794,
    "mu": 0.2558,
    "sigma": 0.0665,
    "lower": 0.1227,
    "upper": 0.3888
  },
  {
    "x": 54.0053,
    "mu": 0.2566,
    "sigma": 0.0668,
    "lower": 0.123,
    "upper": 0.3902
  },
  {
    "x": 54.6312,
    "mu": 0.2574,
    "sigma": 0.067,
    "lower": 0.1233,
    "upper": 0.3915
  },
  {
    "x": 55.257,
    "mu": 0.2582,
    "sigma": 0.0672,
    "lower": 0.1237,
    "upper": 0.3927
  },
  {
    "x": 55.8829,
    "mu": 0.2589,
    "sigma": 0.0674,
    "lower": 0.1241,
    "upper": 0.3937
  },
  {
    "x": 56.5088,
    "mu": 0.2596,
    "sigma": 0.0675,
    "lower": 0.1245,
    "upper": 0.3947
  },
  {
    "x": 57.1347,
    "mu": 0.2602,
    "sigma": 0.0676,
    "lower": 0.125,
    "upper": 0.3954
  },
  {
    "x": 57.7606,
    "mu": 0.2606,
    "sigma": 0.0676,
    "lower": 0.1254,
    "upper": 0.3959
  },
  {
    "x": 58.3865,
    "mu": 0.261,
    "sigma": 0.0676,
    "lower": 0.1258,
    "upper": 0.3962
  },
  {
    "x": 59.0124,
    "mu": 0.2612,
    "sigma": 0.0675,
    "lower": 0.1261,
    "upper": 0.3962
  },
  {
    "x": 59.6383,
    "mu": 0.2612,
    "sigma": 0.0674,
    "lower": 0.1265,
    "upper": 0.3959
  },
  {
    "x": 60.2642,
    "mu": 0.2611,
    "sigma": 0.0672,
    "lower": 0.1267,
    "upper": 0.3954
  },
  {
    "x": 60.8901,
    "mu": 0.2607,
    "sigma": 0.0669,
    "lower": 0.1269,
    "upper": 0.3946
  },
  {
    "x": 61.5159,
    "mu": 0.2602,
    "sigma": 0.0666,
    "lower": 0.127,
    "upper": 0.3935
  },
  {
    "x": 62.1418,
    "mu": 0.2596,
    "sigma": 0.0663,
    "lower": 0.1271,
    "upper": 0.3922
  },
  {
    "x": 62.7677,
    "mu": 0.2589,
    "sigma": 0.0659,
    "lower": 0.1271,
    "upper": 0.3906
  },
  {
    "x": 63.3936,
    "mu": 0.258,
    "sigma": 0.0654,
    "lower": 0.1272,
    "upper": 0.3889
  },
  {
    "x": 64.0195,
    "mu": 0.2571,
    "sigma": 0.0649,
    "lower": 0.1272,
    "upper": 0.387
  },
  {
    "x": 64.6454,
    "mu": 0.2561,
    "sigma": 0.0644,
    "lower": 0.1273,
    "upper": 0.3849
  },
  {
    "x": 65.2713,
    "mu": 0.255,
    "sigma": 0.0639,
    "lower": 0.1273,
    "upper": 0.3828
  },
  {
    "x": 65.8972,
    "mu": 0.2539,
    "sigma": 0.0633,
    "lower": 0.1274,
    "upper": 0.3805
  },
  {
    "x": 66.5231,
    "mu": 0.2528,
    "sigma": 0.0627,
    "lower": 0.1275,
    "upper": 0.3781
  },
  {
    "x": 67.1489,
    "mu": 0.2516,
    "sigma": 0.062,
    "lower": 0.1276,
    "upper": 0.3756
  },
  {
    "x": 67.7748,
    "mu": 0.2504,
    "sigma": 0.0613,
    "lower": 0.1277,
    "upper": 0.3731
  },
  {
    "x": 68.4007,
    "mu": 0.2492,
    "sigma": 0.0607,
    "lower": 0.1278,
    "upper": 0.3705
  },
  {
    "x": 69.0266,
    "mu": 0.2479,
    "sigma": 0.06,
    "lower": 0.128,
    "upper": 0.3679
  },
  {
    "x": 69.6525,
    "mu": 0.2467,
    "sigma": 0.0593,
    "lower": 0.1281,
    "upper": 0.3653
  },
  {
    "x": 70.2784,
    "mu": 0.2455,
    "sigma": 0.0586,
    "lower": 0.1283,
    "upper": 0.3626
  },
  {
    "x": 70.9043,
    "mu": 0.2442,
    "sigma": 0.0579,
    "lower": 0.1285,
    "upper": 0.36
  },
  {
    "x": 71.5302,
    "mu": 0.243,
    "sigma": 0.0572,
    "lower": 0.1286,
    "upper": 0.3574
  },
  {
    "x": 72.1561,
    "mu": 0.2418,
    "sigma": 0.0565,
    "lower": 0.1288,
    "upper": 0.3548
  }
]
